charli/__init__.py
charli/__init__.pyi
charli/charli.cpython-314t-x86_64-linux-gnu.so
swgo_charli-0.3.0.dist-info/METADATA
swgo_charli-0.3.0.dist-info/WHEEL
swgo_charli-0.3.0.dist-info/RECORD
swgo_charli-0.3.0.dist-info/licenses/LICENSE
